{
  "metadata": {
    "name": "IHentai",
    "author": "uBook",
    "slug": "ihentai",
    "version": 2,
    "source": "https://ihentai.de",
    "regexp": "(ihentai).(de)",
    "description": "Đọc truyện 18+ trên trang IHentai",
    "locale": "vi_VN",
    "language": "javascript",
    "type": "video",
    "tabsHome": [
      {
        "title": "Mới tải lên",
        "url": "/search"
      },
      {
        "title": "Top lượt xem",
        "url": "/search?orderby=meta_value_num&order=desc&metaKey=x_post_views_count"
      },
      {
        "title": "Vietsub",
        "url": "/hentai-vietsub"
      },
      {
        "title": "3D",
        "url": "/hentai-3d"
      },
      {
        "title": "Không che",
        "url": "/uncensored"
      }
    ],
    "tag": "18+",
    "genre": true,
    "search": true
  },
  "script": {
    "home": "src/home.js",
    "detail": "src/detail.js",
    "chapters": "src/chapters.js",
    "chapter": "src/chapter.js",
    "genre": "src/genre.js",
    "search": "src/search.js"
  }
}
